astro_observe_sdk/__init__.py
astro_observe_sdk/constants.py
astro_observe_sdk/lineage.py
astro_observe_sdk/metrics.py
astro_observe_sdk/clients/__init__.py
astro_observe_sdk/clients/config.py
astro_observe_sdk/clients/metrics.py
astro_observe_sdk/utils/__init__.py
astro_observe_sdk/utils/airflow.py
astro_observe_sdk/utils/database.py
astro_observe_sdk/utils/observe.py
astro_observe_sdk/utils/openlineage.py
astro_observe_sdk-0.0.10.dist-info/METADATA
astro_observe_sdk-0.0.10.dist-info/WHEEL
astro_observe_sdk-0.0.10.dist-info/licenses/LICENSE
astro_observe_sdk-0.0.10.dist-info/RECORD
