Metadata-Version: 2.4
Name: astro-observe-sdk
Version: 0.0.10
Summary: An Airflow and Python SDK for working with the Astro Observe platform
License-File: LICENSE
Requires-Python: >=3.9
Requires-Dist: apache-airflow-providers-openlineage>=1.10.0
Requires-Dist: apache-airflow>=2.7.0
Requires-Dist: attrs>=20.0
Requires-Dist: openlineage-python>=1.40.1
